maadsbml/__init__.py
maadsbml/balancedata.py
maadsbml/callmas.py
maadsbml/sendfiles.py
maadsbml-1.3.20.dist-info/METADATA
maadsbml-1.3.20.dist-info/WHEEL
maadsbml-1.3.20.dist-info/license.txt
maadsbml-1.3.20.dist-info/top_level.txt
maadsbml-1.3.20.dist-info/RECORD
