Metadata-Version: 2.2
Name: maadsbml
Version: 1.3.20
Summary: Multi-Agent Accelerator for Data Science (MAADS) Batch AutoML (MAADSBML)
Home-page: https://github.com/smaurice101/acnsmauricedsmas
Author: Sebastian Maurice
Author-email: sebastian.maurice@otics.ca
License: MIT License
Keywords: multi-agent, data science, batch automl, optimization, prescriptive analytics, machine learning, automl,auto-ml,artificial intelligence,predictive analytics,advanced analytics
License-File: license.txt
Requires-Dist: aiohttp>=3.6.2
Requires-Dist: requests>=2.22.0
Requires-Dist: validators==0.14.2
Requires-Dist: wheel>=0.33.6
Requires-Dist: numpy>=1.18.1
Requires-Dist: pandas>=0.25.3
Requires-Dist: numpy-indexed>=0.3.5
Requires-Dist: async_timeout
Requires-Dist: asyncio
Requires-Dist: nest_asyncio
Requires-Dist: Fitter
Requires-Dist: stats
Dynamic: author
Dynamic: author-email
Dynamic: description
Dynamic: description-content-type
Dynamic: home-page
Dynamic: keywords
Dynamic: license
Dynamic: requires-dist
Dynamic: summary
